setup.cfg
setup.py
listats/__init__.py
listats/listats.py
listats.egg-info/PKG-INFO
listats.egg-info/SOURCES.txt
listats.egg-info/dependency_links.txt
listats.egg-info/entry_points.txt
listats.egg-info/requires.txt
listats.egg-info/top_level.txt