Metadata-Version: 1.0
Name: listats
Version: 1.0
Summary: LiveInternet stat reader
Home-page: https://github.com/khokhlin/listats/
Author: Andrey Khokhlin
Author-email: khokhlin@gmail.com
License: UNKNOWN
Platform: UNKNOWN
